[{"results": [{"tech":1,"pts":2146,"connections":992326,"capacity":42772022,"investments":508484961},{"tech":5,"pts":7,"connections":11504,"capacity":786713,"investments":4226981},{"tech":4,"pts":4,"connections":28555,"capacity":1377153,"investments":2191357},{"tech":7,"pts":2,"connections":362,"capacity":12222,"investments":139763},{"tech":3,"pts":44457,"connections":1535285,"capacity":105669191,"investments":581180417},{"tech":6,"pts":8,"connections":3878,"capacity":320778,"investments":1377919}]}]