[{"adm":565,"cc":566,"scn":"l1","results":[{"tech":1,"pts":70,"connections":225606,"capacity":187994,"investments":15137059}]},{"adm":566,"cc":566,"scn":"l1","results":[{"tech":1,"pts":135,"connections":48383,"capacity":40328,"investments":6086655},{"tech":2,"pts":675,"connections":140784,"capacity":222008,"investments":304587}]},{"adm":567,"cc":566,"scn":"l1","results":[{"tech":2,"pts":183,"connections":50778,"capacity":80036,"investments":109823},{"tech":1,"pts":730,"connections":327722,"capacity":273132,"investments":39645704}]},{"adm":568,"cc":566,"scn":"l1","results":[{"tech":3,"pts":2,"connections":234,"capacity":622,"investments":3426},{"tech":1,"pts":131,"connections":13002,"capacity":10859,"investments":4091602},{"tech":2,"pts":1848,"connections":203914,"capacity":322103,"investments":442158}]},{"adm":569,"cc":566,"scn":"l1","results":[{"tech":1,"pts":115,"connections":52767,"capacity":43986,"investments":6511983},{"tech":2,"pts":552,"connections":132586,"capacity":208880,"investments":286671}]},{"adm":570,"cc":566,"scn":"l1","results":[{"tech":2,"pts":274,"connections":37722,"capacity":59525,"investments":81681},{"tech":1,"pts":348,"connections":7982,"capacity":6661,"investments":8418447}]},{"adm":571,"cc":566,"scn":"l1","results":[{"tech":2,"pts":72,"connections":22744,"capacity":35849,"investments":49210},{"tech":1,"pts":420,"connections":291798,"capacity":243163,"investments":27448308}]},{"adm":572,"cc":566,"scn":"l1","results":[{"tech":1,"pts":46,"connections":23588,"capacity":19649,"investments":2764836},{"tech":2,"pts":84,"connections":46434,"capacity":73229,"investments":100498}]},{"adm":573,"cc":566,"scn":"l1","results":[{"tech":3,"pts":89,"connections":8428,"capacity":22388,"investments":123060},{"tech":1,"pts":130,"connections":21048,"capacity":17533,"investments":4306833},{"tech":2,"pts":2009,"connections":130416,"capacity":205395,"investments":281916}]},{"adm":574,"cc":566,"scn":"l1","results":[{"tech":1,"pts":127,"connections":189800,"capacity":158150,"investments":14093310},{"tech":2,"pts":732,"connections":99558,"capacity":156960,"investments":215512}]},{"adm":575,"cc":566,"scn":"l1","results":[{"tech":2,"pts":104,"connections":19871,"capacity":31327,"investments":43004},{"tech":1,"pts":80,"connections":120991,"capacity":100831,"investments":9493179}]},{"adm":576,"cc":566,"scn":"l1","results":[{"tech":1,"pts":129,"connections":110597,"capacity":92142,"investments":10009002},{"tech":2,"pts":16,"connections":3492,"capacity":5510,"investments":7565}]},{"adm":577,"cc":566,"scn":"l1","results":[{"tech":1,"pts":15,"connections":5986,"capacity":4988,"investments":826104},{"tech":3,"pts":98,"connections":3220,"capacity":8576,"investments":47167},{"tech":2,"pts":1487,"connections":78009,"capacity":122782,"investments":169067}]},{"adm":578,"cc":566,"scn":"l1","results":[{"tech":1,"pts":90,"connections":15241,"capacity":12693,"investments":3453681},{"tech":2,"pts":377,"connections":101974,"capacity":160926,"investments":220789}]},{"adm":579,"cc":566,"scn":"l1","results":[{"tech":2,"pts":961,"connections":164591,"capacity":259499,"investments":356219},{"tech":1,"pts":469,"connections":138088,"capacity":115055,"investments":19872081}]},{"adm":580,"cc":566,"scn":"l1","results":[{"tech":2,"pts":1283,"connections":101312,"capacity":159653,"investments":219403},{"tech":1,"pts":131,"connections":12484,"capacity":10403,"investments":3656308}]},{"adm":581,"cc":566,"scn":"l1","results":[{"tech":1,"pts":190,"connections":69276,"capacity":57725,"investments":8832738},{"tech":2,"pts":351,"connections":55048,"capacity":86777,"investments":119134}]},{"adm":582,"cc":566,"scn":"l1","results":[{"tech":1,"pts":2,"connections":5359,"capacity":4466,"investments":416919},{"tech":2,"pts":961,"connections":116789,"capacity":183888,"investments":252585}]},{"adm":583,"cc":566,"scn":"l1","results":[{"tech":1,"pts":51,"connections":32012,"capacity":26678,"investments":3229813},{"tech":2,"pts":114,"connections":19624,"capacity":30947,"investments":42498}]},{"adm":584,"cc":566,"scn":"l1","results":[{"tech":1,"pts":542,"connections":187808,"capacity":156572,"investments":23844660},{"tech":2,"pts":79,"connections":9828,"capacity":15487,"investments":21254}]}]