[{"adm":507,"cc":566,"scn":"l2","results":[{"tech":1,"pts":18,"connections":434922,"capacity":3690135,"investments":31100940}]},{"adm":508,"cc":566,"scn":"l2","results":[{"tech":1,"pts":12,"connections":262112,"capacity":2223902,"investments":18717519}]},{"adm":509,"cc":566,"scn":"l2","results":[{"tech":1,"pts":152,"connections":1115454,"capacity":9464210,"investments":91414473}]},{"adm":510,"cc":566,"scn":"l2","results":[{"tech":1,"pts":169,"connections":667531,"capacity":5663692,"investments":58165266}]},{"adm":511,"cc":566,"scn":"l2","results":[{"tech":1,"pts":43,"connections":758752,"capacity":6437692,"investments":53776974}]},{"adm":512,"cc":566,"scn":"l2","results":[{"tech":1,"pts":445,"connections":160336,"capacity":1360814,"investments":26819445},{"tech":2,"pts":49,"connections":13274,"capacity":213019,"investments":292355}]},{"adm":513,"cc":566,"scn":"l2","results":[{"tech":1,"pts":191,"connections":134686,"capacity":1142762,"investments":14707074},{"tech":2,"pts":1016,"connections":77547,"capacity":1245944,"investments":1710060}]},{"adm":514,"cc":566,"scn":"l2","results":[{"tech":1,"pts":187,"connections":223074,"capacity":1892766,"investments":24238367}]},{"adm":515,"cc":566,"scn":"l2","results":[{"tech":2,"pts":255,"connections":39350,"capacity":632102,"investments":867536},{"tech":1,"pts":210,"connections":56522,"capacity":479279,"investments":9984832}]},{"adm":516,"cc":566,"scn":"l2","results":[{"tech":1,"pts":32,"connections":253805,"capacity":2153450,"investments":21001254}]},{"adm":517,"cc":566,"scn":"l2","results":[{"tech":1,"pts":47,"connections":572608,"capacity":4858370,"investments":44033985}]},{"adm":518,"cc":566,"scn":"l2","results":[{"tech":1,"pts":378,"connections":481081,"capacity":4081745,"investments":49112012}]},{"adm":519,"cc":566,"scn":"l2","results":[{"tech":1,"pts":75,"connections":606952,"capacity":5149696,"investments":47423708}]},{"adm":520,"cc":566,"scn":"l2","results":[{"tech":1,"pts":239,"connections":558461,"capacity":4738328,"investments":44343692}]},{"adm":521,"cc":566,"scn":"l2","results":[{"tech":1,"pts":27,"connections":840373,"capacity":7130216,"investments":58788446}]},{"adm":522,"cc":566,"scn":"l2","results":[{"tech":1,"pts":18,"connections":324829,"capacity":2756031,"investments":23998519}]},{"adm":523,"cc":566,"scn":"l2","results":[{"tech":1,"pts":173,"connections":513312,"capacity":4355143,"investments":46092399},{"tech":2,"pts":6,"connections":824,"capacity":13254,"investments":18191}]},{"adm":524,"cc":566,"scn":"l2","results":[{"tech":1,"pts":37,"connections":429379,"capacity":3643099,"investments":33400932}]},{"adm":525,"cc":566,"scn":"l2","results":[{"tech":1,"pts":18,"connections":406599,"capacity":3449806,"investments":29177908}]},{"adm":526,"cc":566,"scn":"l2","results":[{"tech":1,"pts":30,"connections":787005,"capacity":6677386,"investments":55729939}]}]