[{"adm":1,"cc":566,"scn":"l3","results":[{"tech":1,"pts":18,"connections":149922,"capacity":3946649,"investments":21646619}]},{"adm":2,"cc":566,"scn":"l3","results":[{"tech":1,"pts":50,"connections":349727,"capacity":9206420,"investments":49899790}]},{"adm":3,"cc":566,"scn":"l3","results":[{"tech":4,"pts":243,"connections":40793,"capacity":2033714,"investments":7620505},{"tech":2,"pts":8,"connections":786,"capacity":39191,"investments":53786},{"tech":1,"pts":140,"connections":143698,"capacity":3782651,"investments":31968938}]},{"adm":4,"cc":566,"scn":"l3","results":[{"tech":4,"pts":216,"connections":30909,"capacity":1539578,"investments":6076624},{"tech":2,"pts":82,"connections":6498,"capacity":323749,"investments":444303},{"tech":1,"pts":311,"connections":176484,"capacity":4645942,"investments":45187187}]},{"adm":5,"cc":566,"scn":"l3","results":[{"tech":4,"pts":53,"connections":10474,"capacity":522003,"investments":1857386},{"tech":1,"pts":184,"connections":119613,"capacity":3148836,"investments":29836685}]},{"adm":6,"cc":566,"scn":"l3","results":[{"tech":1,"pts":235,"connections":71284,"capacity":1876830,"investments":17996689},{"tech":4,"pts":20,"connections":3936,"capacity":196122,"investments":699060}]},{"adm":7,"cc":566,"scn":"l3","results":[{"tech":1,"pts":221,"connections":69446,"capacity":1827650,"investments":17319357},{"tech":4,"pts":32,"connections":7913,"capacity":394672,"investments":1306957},{"tech":2,"pts":4,"connections":429,"capacity":21438,"investments":29422}]},{"adm":8,"cc":566,"scn":"l3","results":[{"tech":1,"pts":139,"connections":80986,"capacity":2131819,"investments":17677826},{"tech":2,"pts":44,"connections":2656,"capacity":132204,"investments":181429},{"tech":4,"pts":150,"connections":19133,"capacity":954497,"investments":3933088}]},{"adm":9,"cc":566,"scn":"l3","results":[{"tech":4,"pts":52,"connections":7129,"capacity":354754,"investments":1421323},{"tech":2,"pts":1,"connections":96,"capacity":4767,"investments":6543},{"tech":1,"pts":322,"connections":148577,"capacity":3910498,"investments":31681302}]},{"adm":10,"cc":566,"scn":"l3","results":[{"tech":1,"pts":204,"connections":238730,"capacity":6284230,"investments":46552967},{"tech":2,"pts":1,"connections":96,"capacity":4783,"investments":6564},{"tech":4,"pts":367,"connections":58358,"capacity":2905521,"investments":11117674}]},{"adm":11,"cc":566,"scn":"l3","results":[{"tech":2,"pts":1,"connections":107,"capacity":5349,"investments":7341},{"tech":4,"pts":6,"connections":767,"capacity":38301,"investments":157411},{"tech":1,"pts":191,"connections":186882,"capacity":4919476,"investments":32414247}]},{"adm":12,"cc":566,"scn":"l3","results":[{"tech":4,"pts":4,"connections":872,"capacity":43460,"investments":149937},{"tech":1,"pts":105,"connections":40057,"capacity":1054268,"investments":9447824}]},{"adm":13,"cc":566,"scn":"l3","results":[{"tech":4,"pts":50,"connections":5735,"capacity":285516,"investments":1219366},{"tech":2,"pts":44,"connections":3904,"capacity":194174,"investments":266502},{"tech":1,"pts":154,"connections":32487,"capacity":855567,"investments":9973374}]},{"adm":14,"cc":566,"scn":"l3","results":[{"tech":1,"pts":294,"connections":58128,"capacity":1528887,"investments":16938621}]},{"adm":15,"cc":566,"scn":"l3","results":[{"tech":1,"pts":162,"connections":105150,"capacity":2768286,"investments":21833195},{"tech":4,"pts":265,"connections":37972,"capacity":1895262,"investments":7506238},{"tech":2,"pts":30,"connections":942,"capacity":46752,"investments":64162}]},{"adm":16,"cc":566,"scn":"l3","results":[{"tech":7,"pts":1,"connections":126,"capacity":4382,"investments":47493},{"tech":4,"pts":2,"connections":275,"capacity":13665,"investments":54774},{"tech":2,"pts":19,"connections":914,"capacity":45427,"investments":62341},{"tech":1,"pts":209,"connections":325943,"capacity":8580401,"investments":53077513}]},{"adm":17,"cc":566,"scn":"l3","results":[{"tech":1,"pts":130,"connections":55471,"capacity":1460190,"investments":12403121},{"tech":2,"pts":1,"connections":92,"capacity":4602,"investments":6316},{"tech":4,"pts":5,"connections":925,"capacity":46097,"investments":165831}]}]