[{"adm":521,"cc":566,"scn":"n3","results":[{"tech":1,"pts":27,"connections":840373,"capacity":22122772,"investments":110068836}]},{"adm":507,"cc":566,"scn":"n3","results":[{"tech":1,"pts":18,"connections":434922,"capacity":11449305,"investments":57739184}]},{"adm":508,"cc":566,"scn":"n3","results":[{"tech":1,"pts":12,"connections":262112,"capacity":6900048,"investments":34783832}]},{"adm":509,"cc":566,"scn":"n3","results":[{"tech":1,"pts":152,"connections":1115454,"capacity":29364425,"investments":161119621}]},{"adm":510,"cc":566,"scn":"n3","results":[{"tech":1,"pts":169,"connections":667531,"capacity":17572608,"investments":99797014}]},{"adm":511,"cc":566,"scn":"n3","results":[{"tech":1,"pts":43,"connections":758752,"capacity":19974087,"investments":100269816}]},{"adm":512,"cc":566,"scn":"n3","results":[{"tech":3,"pts":17,"connections":963,"capacity":80323,"investments":441774},{"tech":1,"pts":477,"connections":172647,"capacity":4545903,"investments":40065238}]},{"adm":513,"cc":566,"scn":"n3","results":[{"tech":2,"pts":55,"connections":29,"capacity":1431,"investments":1963},{"tech":1,"pts":361,"connections":177346,"capacity":4668901,"investments":38723227},{"tech":7,"pts":13,"connections":1911,"capacity":66684,"investments":848933},{"tech":4,"pts":38,"connections":2504,"capacity":124882,"investments":652577},{"tech":3,"pts":740,"connections":30443,"capacity":2574712,"investments":14160817}]},{"adm":514,"cc":566,"scn":"n3","results":[{"tech":1,"pts":187,"connections":223074,"capacity":5872630,"investments":38235302}]},{"adm":515,"cc":566,"scn":"n3","results":[{"tech":3,"pts":125,"connections":10553,"capacity":892893,"investments":4910888},{"tech":4,"pts":19,"connections":1409,"capacity":70334,"investments":351589},{"tech":1,"pts":321,"connections":83910,"capacity":2207986,"investments":26863060}]},{"adm":516,"cc":566,"scn":"n3","results":[{"tech":1,"pts":32,"connections":253805,"capacity":6681465,"investments":36789126}]},{"adm":517,"cc":566,"scn":"n3","results":[{"tech":1,"pts":47,"connections":572608,"capacity":15073957,"investments":79373464}]},{"adm":518,"cc":566,"scn":"n3","results":[{"tech":1,"pts":378,"connections":481081,"capacity":12664446,"investments":79092463}]},{"adm":519,"cc":566,"scn":"n3","results":[{"tech":1,"pts":75,"connections":606952,"capacity":15977838,"investments":84776911}]},{"adm":520,"cc":566,"scn":"n3","results":[{"tech":1,"pts":239,"connections":558461,"capacity":14701514,"investments":78625156}]},{"adm":522,"cc":566,"scn":"n3","results":[{"tech":1,"pts":18,"connections":324829,"capacity":8551083,"investments":44053163}]},{"adm":523,"cc":566,"scn":"n3","results":[{"tech":1,"pts":175,"connections":513949,"capacity":13529346,"investments":78493434},{"tech":3,"pts":4,"connections":187,"capacity":15659,"investments":86129}]},{"adm":524,"cc":566,"scn":"n3","results":[{"tech":1,"pts":37,"connections":429379,"capacity":11303367,"investments":60100545}]},{"adm":525,"cc":566,"scn":"n3","results":[{"tech":1,"pts":18,"connections":406599,"capacity":10703646,"investments":54132431}]},{"adm":526,"cc":566,"scn":"n3","results":[{"tech":1,"pts":30,"connections":787005,"capacity":20717784,"investments":103869437}]}]